{
  "en": [
    {
      "id": "bms-simulator",
      "title": "Virtual HIL BMS Simulator",
      "slug": "bms-simulator",
      "description": "A 'Hardware-in-the-Loop' (HIL) simulator running real Python BMS control logic inside the browser. Demonstrates advanced QA Automation by verifying safety-critical systems.",
      "techStack": [
        "Next.js 15",
        "Web Workers",
        "Python (Pyodide)",
        "Zustand",
        "Tailwind CSS",
        "Framer Motion"
      ],
      "image": "/images/bms.png",
      "video": "/images/bms.mp4",
      "repoUrl": "https://github.com/JordanLmb/ev-bms-showcase",
      "demoUrl": "https://ev-bms-showcase.vercel.app",
      "isPrivate": false
    },
    {
      "id": "card-value",
      "title": "CardValue - TCG Collection Visualizer",
      "slug": "card-value",
      "description": "Track collection values for Pokemon, Magic, and Yu-Gi-Oh with CSV upload and cloud persistence.",
      "techStack": [
        "Next.js 16",
        "React",
        "TypeScript",
        "TailwindCSS",
        "Framer Motion",
        "Recharts",
        "Supabase"
      ],
      "image": "/images/cardvalue.png",
      "video": "/images/cardvalue.mp4",
      "repoUrl": "https://github.com/JordanLmb/CardValue",
      "demoUrl": "https://jordanlmb.com/CardValue",
      "isPrivate": false
    },
    {
      "id": "portfolio",
      "title": "My Portfolio",
      "slug": "master-portfolio",
      "description": "This very website! A Next.js application showcasing my development journey.",
      "techStack": [
        "Next.js",
        "Tailwind CSS",
        "TypeScript"
      ],
      "image": "/images/portfolio.png",
      "video": "/images/portfolio-demo.mp4",
      "repoUrl": "https://github.com/jordanlmb/portfolio-website",
      "demoUrl": "https://jordanlmb.com",
      "isPrivate": false
    }
  ],
  "fr": [
    {
      "id": "bms-simulator",
      "title": "Simulateur Virtual HIL BMS",
      "slug": "bms-simulator",
      "description": "Simulateur HIL (Hardware-in-the-Loop) exécutant une logique de contrôle BMS Python réelle dans le navigateur. Démontre l'automatisation QA avancée pour les systèmes critiques.",
      "techStack": [
        "Next.js 15",
        "Web Workers",
        "Python (Pyodide)",
        "Zustand",
        "Tailwind CSS",
        "Framer Motion"
      ],
      "image": "/images/bms.png",
      "video": "/images/bms.mp4",
      "repoUrl": "https://github.com/JordanLmb/ev-bms-showcase",
      "demoUrl": "https://ev-bms-showcase.vercel.app",
      "isPrivate": false
    },
    {
      "id": "card-value",
      "title": "CardValue - Visualiseur JCC",
      "slug": "card-value",
      "description": "Suivez la valeur de vos collections Pokemon, Magic et Yu-Gi-Oh avec upload CSV et sauvegarde cloud.",
      "techStack": [
        "Next.js 16",
        "React",
        "TypeScript",
        "TailwindCSS",
        "Framer Motion",
        "Recharts",
        "Supabase"
      ],
      "image": "/images/cardvalue.png",
      "video": "/images/cardvalue.mp4",
      "repoUrl": "https://github.com/JordanLmb/CardValue",
      "demoUrl": "https://jordanlmb.com/CardValue",
      "isPrivate": false
    },
    {
      "id": "portfolio",
      "title": "Mon Portfolio",
      "slug": "master-portfolio",
      "description": "Ce site web ! Une application Next.js présentant mon parcours de développeur.",
      "techStack": [
        "Next.js",
        "Tailwind CSS",
        "TypeScript"
      ],
      "image": "/images/portfolio.png",
      "video": "/images/portfolio-demo.mp4",
      "repoUrl": "https://github.com/jordanlmb/portfolio-website",
      "demoUrl": "https://jordanlmb.com",
      "isPrivate": false
    }
  ]
}